{"lastUsed":1520491070042,"path":"C:\/Users\/teacher\/src\/STM32_IoT_NodeKit","projectCount":3,"recentFiles":[{"path":"\/timer_blinky\/Src","parentWorkspace":"C:\/Users\/teacher\/src\/STM32_IoT_NodeKit","name":"main.c","lastModified":1520491070309,"locationURI":"file:\/C:\/Users\/teacher\/src\/STM32_IoT_NodeKit\/timer_blinky\/Src\/main.c"},{"path":"\/button\/Src","parentWorkspace":"C:\/Users\/teacher\/src\/STM32_IoT_NodeKit","name":"main.c","lastModified":1520487323334,"locationURI":"file:\/C:\/Users\/teacher\/src\/STM32_IoT_NodeKit\/button\/Src\/main.c"},{"path":"\/timer_blinky\/Src","parentWorkspace":"C:\/Users\/teacher\/src\/STM32_IoT_NodeKit","name":"stm32l4xx_it.c","lastModified":1520491070309,"locationURI":"file:\/C:\/Users\/teacher\/src\/STM32_IoT_NodeKit\/timer_blinky\/Src\/stm32l4xx_it.c"},{"path":"\/button\/Src","parentWorkspace":"C:\/Users\/teacher\/src\/STM32_IoT_NodeKit","name":"stm32l4xx_it.c","lastModified":1520487323334,"locationURI":"file:\/C:\/Users\/teacher\/src\/STM32_IoT_NodeKit\/button\/Src\/stm32l4xx_it.c"}]}